zendesk/__init__.py
zendesk/base.py
zendesk/ticket.py
zendesk/ticket_field.py
zendesk/user.py
zendesk_api-0.1.5.dist-info/DESCRIPTION.rst
zendesk_api-0.1.5.dist-info/METADATA
zendesk_api-0.1.5.dist-info/RECORD
zendesk_api-0.1.5.dist-info/WHEEL
zendesk_api-0.1.5.dist-info/metadata.json
zendesk_api-0.1.5.dist-info/top_level.txt
